ph_units/__init__.py
ph_units/converter.py
ph_units/parser.py
ph_units/unit_type.py
ph_units/unit_types/__init__.py
ph_units/unit_types/_base.py
ph_units/unit_types/area.py
ph_units/unit_types/density.py
ph_units/unit_types/emissions_factors.py
ph_units/unit_types/energy.py
ph_units/unit_types/envelope.py
ph_units/unit_types/hvac.py
ph_units/unit_types/length.py
ph_units/unit_types/moisture_vapor_resistance.py
ph_units/unit_types/power.py
ph_units/unit_types/speed.py
ph_units/unit_types/temperature.py
ph_units/unit_types/volume.py
ph_units/unit_types/volume_flow.py
ph_units-1.5.26.dist-info/licenses/LICENSE
ph_units-1.5.26.dist-info/METADATA
ph_units-1.5.26.dist-info/WHEEL
ph_units-1.5.26.dist-info/top_level.txt
ph_units-1.5.26.dist-info/RECORD
