Metadata-Version: 2.4
Name: ph_units
Version: 1.5.26
Summary: Tools for working with common Passive House unit types
Home-page: https://github.com/PH-Tools/PH_units
Author: PH-Tools
Author-email: phtools@bldgtyp.com
License: GPLv3+
Classifier: Programming Language :: Python :: 2
Classifier: Programming Language :: Python :: 2.7
Classifier: Programming Language :: Python :: 3
Classifier: Programming Language :: Python :: 3.10
Classifier: Programming Language :: Python :: Implementation :: CPython
Classifier: License :: OSI Approved :: GNU General Public License v3 or later (GPLv3+)
Classifier: Operating System :: OS Independent
Classifier: Typing :: Typed
License-File: LICENSE
Dynamic: description
Dynamic: description-content-type
Dynamic: license-file
